{
	"info": {
		"id": "cc\\madhya\\8\\304",
		"nextId": "cc/madhya/8/305",
		"prevId": "cc/madhya/8/303"
	},
	"verses": [
		{
			"roman": "sahaje caitanya-caritra--ghana-dugdha-pūra\nrāmānanda-caritra tāhe khaṇḍa pracura\n",
			"isProse": false
		}
	],
	"synonyms": "sahaje—generally; caitanya-caritra—the activities of Śrī Caitanya Mahāprabhu; ghana-dugdha-pūra—like condensed milk; rāmānanda-caritra—the story of Rāmānanda Rāya; tāhe—in that; khaṇḍa—sugar candy; pracura—a large quantity.",
	"translation": "The activities of Śrī Caitanya Mahāprabhu are like condensed milk, and the activities of Rāmānanda Rāya are like large quantities of sugar candy."
}