{
	"info": {
		"id": "cc\\antya\\18\\41",
		"nextId": "cc/antya/18/42",
		"prevId": "cc/antya/18/40"
	},
	"verses": [
		{
			"roman": "samudrera tīre āsi' yukati karilā\ncirāyu-parvata-dike kata-jana gelā\n",
			"isProse": false
		}
	],
	"synonyms": "samudrera tīre—on the seashore; āsi'-coming; yukati karilā—they consulted among themselves; cirāyu-parvata—of Caṭaka-parvata; dike—in the direction; kata-jana—some of them; gelā—went.",
	"translation": "When they arrived at the seashore, they conferred among themselves. Then some of them sought out Śrī Caitanya Mahāprabhu at Caṭaka-parvata."
}