{
	"info": {
		"id": "cc\\madhya\\10\\59",
		"nextId": "cc/madhya/10/60",
		"prevId": "cc/madhya/10/58"
	},
	"verses": [
		{
			"roman": "dina-pāṅca-sāta bhitare āsibe rāmānanda\ntāṅra saṅge pūrṇa habe āmāra ānanda\n",
			"isProse": false
		}
	],
	"synonyms": "dina-pāṅca-sāta—five or seven days; bhitare—within; āsibe—will come; rāmānanda—Rāmānanda; tāṅra saṅge—with him; pūrṇa habe—will be full; āmāra—My; ānanda—pleasure.",
	"translation": "\"Śrī Rāmānanda Rāya is coming within five to seven days. As soon as he arrives, My desires will be fulfilled. I take great pleasure in his company.\""
}