{
	"info": {
		"id": "cc\\madhya\\10\\62",
		"nextId": "cc/madhya/10/63",
		"prevId": "cc/madhya/10/61"
	},
	"verses": [
		{
			"roman": "bhaṭṭācārya saba loke vidāya karāila\ntabe prabhu kālā-kṛṣṇadāse bolāila\n",
			"isProse": false
		}
	],
	"synonyms": "bhaṭṭācārya—Sārvabhauma Bhaṭṭācārya; saba loke—all persons; vidāya karāila—asked to leave; tabe—at that time; prabhu—Śrī Caitanya Mahāprabhu; kālā-kṛṣṇadāse—Kālā Kṛṣṇadāsa; bolāila—called for.",
	"translation": "Sārvabhauma Bhaṭṭācārya then asked all the people to leave. Afterward, Śrī Caitanya Mahāprabhu called for Kālā Kṛṣṇadāsa, who had accompanied the Lord during His South Indian tour."
}