{
	"info": {
		"id": "cc\\antya\\3\\65",
		"nextId": "cc/antya/3/66",
		"prevId": "cc/antya/3/64"
	},
	"verses": [
		{
			"roman": "nāmābhāse 'mukti' haya sarva-śāstre dekhi\nśrī-bhāgavate tāte ajāmila--sākṣī\"\n",
			"isProse": false
		}
	],
	"synonyms": "nāma-ābhāse—simply by a glimpse of the rays of the holy name; mukti—liberation; haya—there is; sarva-śāstre—in all the revealed scriptures; dekhi—I find; śrī-bhāgavate—in Śrīmad-Bhāgavatam; tāte—to that; ajāmila—Ajāmila; sākṣī—witness.",
	"translation": "\"Because of even the faintest rays of the effulgence of the Lord's holy name, one ca attain liberation. We can see this in all the revealed scriptures. The evidence appears in the story of Ajāmila in Śrīmad-Bhāgavatam.\""
}