{
	"info": {
		"id": "cc\\madhya\\11\\213",
		"nextId": "cc/madhya/11/214",
		"prevId": "cc/madhya/11/212"
	},
	"verses": [
		{
			"roman": "sabā lañā gelā prabhu jagannāthālaya\nkīrtana ārambha tathā kaila mahāśaya\n",
			"isProse": false
		}
	],
	"synonyms": "sabā lañā—taking all of them; gelā—went; prabhu—Śrī Caitanya Mahāprabhu; jagannātha-ālaya—to the temple of Lord Jagannātha; kīrtana—congregational chanting; ārambha—beginning; tathā—there; kaila—did; mahāśaya—the great personality.",
	"translation": "The great Personality of Godhead, Śrī Caitanya Mahāprabhu, then took all of them to the temple of Jagannātha and began the congregational chanting of the holy name there."
}