{
	"info": {
		"id": "cc\\antya\\12\\141",
		"nextId": "cc/antya/12/142",
		"prevId": "cc/antya/12/140"
	},
	"verses": [
		{
			"roman": "candanādi lañā prabhu vasilā sei sthāne\n'āmāra āge āji tumi karaha bhojane'\n",
			"isProse": false
		}
	],
	"synonyms": "candana-ādi lañā—accepting the sandalwood pulp and other items; prabhu—Śrī Caitanya Mahāprabhu; vasilā—sat down; sei sthāne—at that place; āmāra āge—in front of Me; āji—now; tumi—you; karaha—perform; bhojane—eating.",
	"translation": "Accepting the sandalwood pulp and garland, the Lord sat down and said, \"Now, in front of Me, you must eat.\""
}