{
	"info": {
		"id": "cc\\madhya\\23\\44",
		"nextId": "cc/madhya/23/45",
		"prevId": "cc/madhya/23/43"
	},
	"verses": [
		{
			"roman": "ihā yaiche krame nirmala, krame bāḍe svāda\nrati-premādira taiche bāḍaye āsvāda\n",
			"isProse": false
		}
	],
	"synonyms": "ihā—this; yaiche—like; krame—by succession; nirmala—pure; krame—gradually; bāḍe—increases; svāda—taste; rati—from attachment; prema-ādira—of love of Godhead and so on; taiche—in that way; bāḍaye—increases; āsvāda—taste.",
	"translation": "\"Just as the taste of sugar increases as it is gradually purified, one should understand that when love of Godhead increases from rati, which is compared to the beginning seed, its taste increases."
}