{
	"info": {
		"id": "cc\\madhya\\24\\33",
		"nextId": "cc/madhya/24/34",
		"prevId": "cc/madhya/24/32"
	},
	"verses": [
		{
			"roman": "sakhā-gaṇera rati haya 'anurāga' paryanta\npitṛ-mātṛ-sneha ādi 'anurāga'-anta\n",
			"isProse": false
		}
	],
	"synonyms": "sakhā-gaṇera—of the friends; rati—the attraction; haya—becomes; anurāga paryanta—up to subecstatic love; pitṛ-mātṛ-sneha—paternal love; ādi—and so on; anurāga-anta—up to the end of subecstatic love.",
	"translation": "\"Devotees in Vṛndāvana who are friends of the Lord can increase their ecstatic love to the point of anurāga. Paternal affectionate lovers, Kṛṣṇa's father and mother, can increase their love of Godhead up to the anurāga point also."
}