{
	"info": {
		"id": "cc\\madhya\\24\\353",
		"nextId": "cc/madhya/24/354",
		"prevId": "cc/madhya/24/352"
	},
	"verses": [
		{
			"roman": "'kṛṣṇa-prema', 'bhakti-rasa', 'bhaktira siddhānta'\nihāra śravaṇe bhakta jānena saba anta\n",
			"isProse": false
		}
	],
	"synonyms": "kṛṣṇa-prema—love of Godhead; bhakti-rasa—the mellows of devotional service; bhaktira siddhānta—the conclusions of devotional service; ihāra śravaṇe—by hearing this chapter; bhakta—a devotee; jānena—knows; saba—all; anta—limits.",
	"translation": "By reading this chapter, a pure devotee can understand love of Kṛṣṇa, the mellows of devotional service and the conclusion of devotional service. Everyone can understand all these things to their ultimate end by studying this chapter."
}