{
	"info": {
		"id": "cc\\adi\\5\\157",
		"nextId": "cc/adi/5/158",
		"prevId": "cc/adi/5/156"
	},
	"verses": [
		{
			"roman": "nityānanda-mahimā-sindhu ananta, apāra\neka kaṇā sparśi mātra,--se kṛpā tāṅhāra\n",
			"isProse": false
		}
	],
	"synonyms": "nityānanda-mahimā—of the glories of Lord Nityānanda; sindhu—the ocean; ananta—unlimited; apāra—unfathomed; eka kaṇā—one fragment; sparśi—I touch; mātra—only; se—that; kṛpā—mercy; tāṅhāra—His.",
	"translation": "The ocean of Lord Nityānanda's glories is infinite and unfathomable. Only by His mercy can I touch even a drop of it."
}