{
	"info": {
		"id": "cc\\adi\\17\\270",
		"nextId": "cc/adi/17/271",
		"prevId": "cc/adi/17/269"
	},
	"verses": [
		{
			"roman": "tumi ta' īśvara baṭa,--sākṣāt nārāyaṇa\nkṛpā kari' kara mora saṁsāra mocana\n",
			"isProse": false
		}
	],
	"synonyms": "tumi—you; ta'-certainly; īśvara—the Lord; baṭa—are; sākṣāt—directly; nārāyaṇa—the Supreme Lord, Nārāyaṇa; kṛpā kari'-showing mercy; kara—please do; mora—My; saṁsāra—material life; mocana—deliverance.",
	"translation": "\"Sir, you are directly Nārāyaṇa. Therefore please be merciful unto Me. Deliver Me from this material bondage.\""
}