{
	"info": {
		"id": "cc\\adi\\2\\50",
		"nextId": "cc/adi/2/51",
		"prevId": "cc/adi/2/49"
	},
	"verses": [
		{
			"roman": "sei tina jala-śāyī sarva-antaryāmī\nbrahmāṇḍa-vṛndera ātmā ye puruṣa-nāmī\n",
			"isProse": false
		}
	],
	"synonyms": "sei—these; tina—three; jala-śāyī—lying in the water; sarva—of all; antaḥ yāmī—the Supersoul; brahma-aṇḍa—of universes; vṛndera—of the multitude; ātmā—Supersoul; ye—who; puruṣa—puruṣa; nāmī—named.",
	"translation": "\"These three Viṣṇus lying in the water are the Supersoul of everything. The Supersoul of all the universes is known as the first puruṣa."
}