{
	"info": {
		"id": "cc\\madhya\\16\\250",
		"nextId": "cc/madhya/16/251",
		"prevId": "cc/madhya/16/249"
	},
	"verses": [
		{
			"roman": "tabe navadvīpe tāṅre dila pāṭhāñā\nnīlādri calilā saṅge bhakta-gaṇa lañā\n",
			"isProse": false
		}
	],
	"synonyms": "tabe—thereafter; navadvīpe—to Navadvīpa; tāṅre—her; dila pāṭhāñā—sent back; nīlādri—to Jagannātha Purī; calilā—departed; saṅge—with Him; bhakta-gaṇa lañā—taking all the devotees.",
	"translation": "Śrīmatī Śacīdevī was sent back to Navadvīpa, and the Lord and His devotees started for Jagannātha Purī, Nīlādri."
}