{
	"info": {
		"id": "cc\\madhya\\16\\51",
		"nextId": "cc/madhya/16/52",
		"prevId": "cc/madhya/16/50"
	},
	"verses": [
		{
			"roman": "rāḍhī eka vipra, teṅho--nityānanda dāsa\nmahā-bhāgyavān teṅho, nāma--kṛṣṇadāsa\n",
			"isProse": false
		}
	],
	"synonyms": "rāḍhī eka vipra—one brāhmaṇa resident of Rāḍha-deśa (where the Ganges does not flow); teṅho—he; nityānanda dāsa—servant of Lord Nityānanda; mahā-bhāgyavān—greatly fortunate; teṅho—he; nāma—named; kṛṣṇadāsa—Kṛṣṇadāsa.",
	"translation": "One brāhmaṇa named Kṛṣṇadāsa, who was a resident of Rāḍha-deśa and a servant of Lord Nityānanda's, was a very fortunate person."
}