{
	"info": {
		"id": "cc\\adi\\4\\4",
		"nextId": "cc/adi/4/5",
		"prevId": "cc/adi/4/3"
	},
	"verses": [
		{
			"roman": "mūla-ślokera artha karite prakāśa\nartha lāgāite āge kahiye ābhāsa\n",
			"isProse": false
		}
	],
	"synonyms": "mūla—original; ślokera—of the verse; artha—the meaning; karite—to make; prakāśa—revelation; artha—the meaning; lāgāite—to touch; āge—first; kahiye—I shall speak; ābhāsa—hint.",
	"translation": "Just to explain the original verse, I shall first suggest its meaning."
}