{
	"info": {
		"id": "cc\\adi\\4\\87",
		"nextId": "cc/adi/4/88",
		"prevId": "cc/adi/4/86"
	},
	"verses": [
		{
			"roman": "kṛṣṇa-vāñchā-pūrti-rūpa kare ārādhane\nataeva 'rādhikā' nāma purāṇe vākhāne\n",
			"isProse": false
		}
	],
	"synonyms": "kṛṣṇa-vāñchā—of the desire of Lord Kṛṣṇa; pūrti-rūpa—of the nature of fulfillment; kare—does; ārādhane—worship; ataeva—therefore; rādhikā—Śrīmatī Rādhikā; nāma—named; purāṇe—in the Purāṇas; vākhāne—in the description.",
	"translation": "Her worship [ārādhana] consists of fulfilling the desires of Lord Kṛṣṇa. Therefore the Purāṇas call Her Rādhikā.",
	"purport": [
		{
			"type": "normal",
			"content": "The name Rādhā is derived from the root word ārādhana, which means \"worship.\" The personality who excels all in worshiping Kṛṣṇa may therefore be called Rādhikā, the greatest servitor."
		}
	]
}