{
	"info": {
		"id": "cc\\madhya\\4\\136",
		"nextId": "cc/madhya/4/137",
		"prevId": "cc/madhya/4/135"
	},
	"verses": [
		{
			"roman": "kṣīrera vṛttānta tāṅre kahila pūjārī\nśuni' premāviṣṭa haila śrī-mādhava-purī\n",
			"isProse": false
		}
	],
	"synonyms": "kṣīrera vṛttānta—all the incidents that took place on account of the pot of sweet rice; tāṅre—to Mādhavendra Purī; kahila—explained; pūjārī—the priest; śuni'-hearing; prema-āviṣṭa—saturated with love of Godhead; haila—became; śrī-mādhava-purī—Śrīla Mādhavendra Purī.",
	"translation": "When the story about the pot of sweet rice was explained to him in detail, Śrī Mādhavendra Purī at once became absorbed in ecstatic love of Kṛṣṇa."
}