{
	"info": {
		"id": "cc\\adi\\10\\5",
		"nextId": "cc/adi/10/6",
		"prevId": "cc/adi/10/4"
	},
	"verses": [
		{
			"roman": "yata yata mahānta kailā tāṅ-sabāra gaṇana\nkeha karibāre nāre jyeṣṭha-laghu-krama\n",
			"isProse": false
		}
	],
	"synonyms": "yata yata—as many as there are; mahānta—great devotees; kailā—made; tāṅ-sabāra—of all of them; gaṇana—counting; keha—all of them; karibāre nāre—can not do; jyeṣṭha—elder; laghu—younger; krama—chronology.",
	"translation": "All the great personalities in the line of Lord Caitanya enumerated these devotees, but they could not distinguish between the greater and the lesser."
}