{
	"info": {
		"id": "cc\\madhya\\25\\215",
		"nextId": "cc/madhya/25/216",
		"prevId": "cc/madhya/25/214"
	},
	"verses": [
		{
			"roman": "mathurā-māhātmya-śāstra saṅgraha kariyā\nlupta-tīrtha prakaṭa kailā vanete bhramiyā\n",
			"isProse": false
		}
	],
	"synonyms": "mathurā-māhātmya—giving a description of the greatness of Mathurā; śāstra—books; saṅgraha kariyā—collecting; lupta-tīrtha—lost holy places; prakaṭa—discovering; kailā—he did; vanete bhramiyā—traveling within the forest.",
	"translation": "Śrīla Sanātana Gosvāmī collected some books about archaeological excavations in Mathurā, and, wandering in the forest, he sought to renovate all those holy places."
}