{
	"info": {
		"id": "cc\\antya\\5\\34",
		"nextId": "cc/antya/5/35-36",
		"prevId": "cc/antya/5/33"
	},
	"verses": [
		{
			"roman": "tabe miśra rāmānandera vṛttānta kahilā\nśuni' mahāprabhu tabe kahite lāgilā\n",
			"isProse": false
		}
	],
	"synonyms": "tabe—thereupon; miśra—Pradyumna Miśra; rāmānandera—of Śrī Rāmānanda Rāya; vṛttānta kahilā—described the activities; śuni'-hearing; mahāprabhu—Śrī Caitanya Mahāprabhu; tabe—then; kahite lāgilā—began to speak.",
	"translation": "Pradyumna Miśra thereupon described the activities of Śrī Rāmānanda Rāya. After hearing about these activities, Śrī Caitanya Mahāprabhu began to speak."
}