{
	"info": {
		"id": "cc\\madhya\\19\\58",
		"nextId": "cc/madhya/19/59",
		"prevId": "cc/madhya/19/57"
	},
	"verses": [
		{
			"roman": "madhyāhna karite vipra prabhure kahilā\nrūpa-gosāñi se-divasa tathāñi rahilā\n",
			"isProse": false
		}
	],
	"synonyms": "madhyāhna karite—to accept lunch; vipra—the brāhmaṇa of Deccan; prabhure—Śrī Caitanya Mahāprabhu; kahilā—requested; rūpa-gosāñi—Rūpa Gosvāmī; se-divasa—that day; tathāñi—there; rahilā—remained.",
	"translation": "Śrī Caitanya Mahāprabhu was then requested by the brāhmaṇa to accept His lunch. Rūpa Gosvāmī also remained there that day."
}