{
	"info": {
		"id": "cc\\madhya\\19\\87",
		"nextId": "cc/madhya/19/88",
		"prevId": "cc/madhya/19/86"
	},
	"verses": [
		{
			"roman": "gandha-puṣpa-dhūpa-dīpe mahā-pūjā kaila\nbhaṭṭācārye mānya kari' pāka karāila\n",
			"isProse": false
		}
	],
	"synonyms": "gandha—scents; puṣpa—flowers; dhūpa—incense; dīpe—by lamps; mahā-pūjā kaila—he worshiped the Lord with great pomp; bhaṭṭācārye—to Balabhadra Bhaṭṭācārya; mānya kari'-offering respect; pāka karāila—engaging in cooking.",
	"translation": "Vallabhācārya worshiped the Lord with great pomp, offering scents, incense, flowers and lamps, and with great respect he induced Balabhadra Bhaṭṭa [the Lord's cook] to cook."
}