{
	"info": {
		"id": "cc\\adi\\16\\103",
		"nextId": "cc/adi/16/104",
		"prevId": "cc/adi/16/102"
	},
	"verses": [
		{
			"roman": "śaiśava-cāpalya kichu nā labe āmāra\nśiṣyera samāna muñi nā haṅ tomāra\n",
			"isProse": false
		}
	],
	"synonyms": "śaiśava—childish; cāpalya—impudence; kichu—anything; nā—do not; labe—please take; āmāra—My; śiṣyera—of disciples; samāna—the equal; muñi—I; na—not; haṅ—am; tomāra—your.",
	"translation": "\"I am not even fit to be your disciple. Therefore kindly do not take seriously whatever childish impudence I have shown."
}