{
	"info": {
		"id": "cc\\antya\\8\\4",
		"nextId": "cc/antya/8/5",
		"prevId": "cc/antya/8/3"
	},
	"verses": [
		{
			"roman": "jaya jaya advaita īśvara avatāra\nkṛṣṇa avatāri' kaila jagat-nistāra\n",
			"isProse": false
		}
	],
	"synonyms": "jaya jaya-all glories; advaita-to Advaita Ācārya; īśvara-of the Supreme Personality of Godhead; avatāra-incarnation; kṛṣṇa avatāri'-inducing Kṛṣṇa to descend; kaila-did; jagat-nistāra-deliverance of the entire world.",
	"translation": "All glories to Advaita Prabhu, the incarnation of the Supreme Personality of Godhead. He induced Kṛṣṇa to descend and thus delivered the entire world."
}