{
	"info": {
		"id": "cc\\madhya\\9\\226",
		"nextId": "cc/madhya/9/227",
		"prevId": "cc/madhya/9/225"
	},
	"verses": [
		{
			"roman": "gosāñira saṅge rahe kṛṣṇadāsa brāhmaṇa\nbhaṭṭathāri-saha tāhāṅ haila daraśana\n",
			"isProse": false
		}
	],
	"synonyms": "gosāñira—the Lord; saṅge—with; rahe—there was; kṛṣṇadāsa brāhmaṇa—a brāhmaṇa servant named Kṛṣṇadāsa; bhaṭṭathāri-saha—with the Bhaṭṭathāris; tāhāṅ—there; haila—there was; daraśana—a meeting.",
	"translation": "Śrī Caitanya Mahāprabhu was accompanied by His servant, Kṛṣṇadāsa. He was a brāhmaṇa, but he met with the Bhaṭṭathāris there."
}