{
	"info": {
		"id": "cc\\madhya\\9\\247",
		"nextId": "cc/madhya/9/248",
		"prevId": "cc/madhya/9/246"
	},
	"verses": [
		{
			"roman": "gopī-candana-tale āchila ḍiṅgāte\nmadhvācārya sei kṛṣṇa pāilā kona-mate\n",
			"isProse": false
		}
	],
	"synonyms": "gopī-candana-tale—under heaps of gopī-candana (yellowish clay used for tilaka); āchila—came; ḍiṅgāte—in a boat; madhva-ācārya—Madhvācārya; sei kṛṣṇa—that Kṛṣṇa Deity; pāilā—got; kona-mate—somehow or other.",
	"translation": "Madhvācārya had somehow or other acquired the Deity of Kṛṣṇa from a heap of gopī-candana that had been transported in a boat."
}