{
	"info": {
		"id": "cc\\madhya\\9\\55",
		"nextId": "cc/madhya/9/56",
		"prevId": "cc/madhya/9/54"
	},
	"verses": [
		{
			"roman": "bauddha-gaṇera upare anna paḍe amedhya haiyā\nbauddhācāryera māthāya thāli paḍila bājiyā\n",
			"isProse": false
		}
	],
	"synonyms": "bauddha-gaṇera—all the Buddhists; upare—upon; anna—the food; paḍe—began to fall down; amedhya—untouchable; haiyā—being; bauddha-ācāryera—of the teacher of the Buddhists; māthāya—on the head; thāli—the plate; paḍila—fell down; bājiyā—making a great sound.",
	"translation": "Indeed, the untouchable food fell upon the Buddhists, and the large bird dropped the plate on the head of the chief Buddhist teacher. When it fell on his head, it made a big sound."
}