{
	"info": {
		"id": "cc\\antya\\9\\96",
		"nextId": "cc/antya/9/97",
		"prevId": "cc/antya/9/95"
	},
	"verses": [
		{
			"roman": "kon chāra padārtha ei dui-lakṣa kāhana?\nprāṇa-rājya karoṅ prabhu-pade nirmañchana\"\n",
			"isProse": false
		}
	],
	"synonyms": "kon—what; chāra—little; padārtha—matter; ei—this; dui-lakṣa kāhana—the lotus feet of Śrī Caitanya Mahāprabhu; nirmañchana—sacrificing.",
	"translation": "\"I do not care about this small sum of 200,000 kāhanas. Not to speak of this, I would indeed sacrifice everything at the lotus feet of the Lord, including my life and kingdom.\""
}