{
	"info": {
		"id": "cc\\madhya\\20\\360",
		"nextId": "cc/madhya/20/361",
		"prevId": "cc/madhya/20/359"
	},
	"verses": [
		{
			"roman": "ei śloke 'paraṁ'-śabde 'kṛṣṇa'-nirūpaṇa\n'satyaṁ' śabde kahe tāṅra svarūpa-lakṣaṇa\n",
			"isProse": false
		}
	],
	"synonyms": "ei śloke—in this verse; param-śabde—by the word param, or supreme; kṛṣṇa—of Lord Kṛṣṇa; nirūpaṇa—there is an indication; satyam śabde—by the word satyam, or Absolute Truth; kahe—indicates; tāṅra—His; svarūpa-lakṣaṇa—personal characteristics.",
	"translation": "\"In this invocation from Śrīmad-Bhāgavatam, the word param indicates Lord Kṛṣṇa, the Supreme Personality of Godhead, and the word satyam indicates His personal characteristics."
}