{
	"info": {
		"id": "cc\\madhya\\20\\402",
		"nextId": "cc/madhya/20/403",
		"prevId": "cc/madhya/20/401"
	},
	"verses": [
		{
			"roman": "ei kṛṣṇa--vraje 'pūrṇatama' bhagavān\nāra saba svarūpa--'pūrṇatara' 'pūrṇa' nāma\n",
			"isProse": false
		}
	],
	"synonyms": "ei kṛṣṇa—the same Kṛṣṇa; vraje—Vṛndāvana; pūrṇa-tama bhagavān—the most complete manifestation of the Supreme Personality of Godhead; āra—other; saba—all; sva-rūpa—forms; pūrṇa-tara—more complete; pūrṇa—complete; nāma—named.",
	"translation": "\"Lord Kṛṣṇa is the most complete Supreme Personality of Godhead in Vṛndāvana. Elsewhere all His expansions are either complete or more complete."
}