{
	"info": {
		"id": "cc\\madhya\\20\\73",
		"nextId": "cc/madhya/20/74",
		"prevId": "cc/madhya/20/72"
	},
	"verses": [
		{
			"roman": "pāda-prakṣālana kari' bhikṣāte vasilā\n'sanātane bhikṣā deha'--miśrere kahilā\n",
			"isProse": false
		}
	],
	"synonyms": "pāda-prakṣālana—washing the feet; kari'-doing; bhikṣāte—to lunch; vasilā—sat down; sanātane bhikṣā deha—give Sanātana also lunch; miśrere kahilā—He asked Tapana Miśra.",
	"translation": "After washing His feet, Śrī Caitanya Mahāprabhu sat down for lunch. He asked Tapana Miśra to supply Sanātana Gosvāmī lunch also."
}