{
	"info": {
		"id": "cc\\antya\\6\\148",
		"nextId": "cc/antya/6/149",
		"prevId": "cc/antya/6/147"
	},
	"verses": [
		{
			"roman": "tabe rāghava-paṇḍita tāṅre ghare lañā gelā\nṭhākura darśana karāñā mālā-candana dilā\n",
			"isProse": false
		}
	],
	"synonyms": "tabe—thereupon; rāghava-paṇḍita—Rāghava Paṇḍita; tāṅre—him; ghare lañā gelā—took to his home; ṭhākura darśana karāñā—after inducing him to see the Deity; mālā-candana—a garland and sandalwood pulp; dilā—delivered.",
	"translation": "Thereupon, Rāghava Paṇḍita took Raghunātha dāsa to his home. After inducing him to see the Deity, he gave Raghunātha dāsa a garland and sandalwood pulp."
}