{
	"info": {
		"id": "cc\\antya\\6\\6",
		"nextId": "cc/antya/6/7",
		"prevId": "cc/antya/6/5"
	},
	"verses": [
		{
			"roman": "rāmānandera kṛṣṇa-kathā, svarūpera gāna\nviraha-vedanāya prabhura rākhaye parāṇa\n",
			"isProse": false
		}
	],
	"synonyms": "rāmānandera—of Rāmānanda Rāya; kṛṣṇa-kathā—talks of Lord Kṛṣṇa; svarūpera gāna—the songs of Svarūpa Dāmodara; viraha-vedanāya—at the time of pangs of separation; prabhura—of Lord Śrī Caitanya Mahāprabhu; rākhaye—keep; parāṇa—the life.",
	"translation": "When the Lord acutely felt pangs of separation from Kṛṣṇa, only Śrī Rāma-nanda Rāya's talk about Kṛṣṇa and the sweet songs of Svarūpa Dāmodara kept Him alive."
}