{
	"info": {
		"id": "cc\\antya\\6\\60",
		"nextId": "cc/antya/6/61",
		"prevId": "cc/antya/6/59"
	},
	"verses": [
		{
			"roman": "cabutarā-upare yata prabhura nija-gaṇe\nbaḍa baḍa loka vasilā maṇḍalī-racane\n",
			"isProse": false
		}
	],
	"synonyms": "cabutarā-upare—on the raised platform; yata—all; prabhura nija-gaṇe—very intimate associates of the Lord; baḍa baḍa loka—big, big people; vasilā—sat down; maṇḍalī-racane—in a circle.",
	"translation": "On that platform, all the most important associates of Śrī Nityānanda Prabhu, as well as other important men, sat down in a circle around the Lord."
}