{
	"info": {
		"id": "cc\\antya\\6\\68",
		"nextId": "cc/antya/6/69",
		"prevId": "cc/antya/6/67"
	},
	"verses": [
		{
			"roman": "kona kona vipra upare sthāna nā pāñā\ndui holnāya ciḍā bhijāya gaṅgā-tīre giyā\n",
			"isProse": false
		}
	],
	"synonyms": "kona kona—some; vipra—brāhmaṇas; upare—on the platform; sthāna nā pāñā—not having gotten a place; dui holnāya—in two earthen pots; ciḍā bhijāya—soak chipped rice; gaṅgā-tīre—on the bank of the Ganges; giyā—going.",
	"translation": "Some of the brāhmaṇas, not having gotten a place on the platform, went to the bank of the Ganges with their two earthen pots and soaked their chipped rice there."
}