{
	"info": {
		"id": "cc\\madhya\\15\\227",
		"nextId": "cc/madhya/15/228",
		"prevId": "cc/madhya/15/226"
	},
	"verses": [
		{
			"roman": "kṛṣṇera bhoga lāgāñācha,--anumāna kari\nupare dekhiye yāte tulasī-mañjarī\n",
			"isProse": false
		}
	],
	"synonyms": "kṛṣṇera bhoga lāgāñācha—you have offered to Kṛṣṇa; anumāna kari—I hope; upare—upon the food; dekhiye—I see; yāte—since; tulasī-mañjarī—flowers of the tulasī tree.",
	"translation": "\"I hope the food has already been offered to Kṛṣṇa, since I see there are tulasī flowers over the plates."
}