{
	"info": {
		"id": "cc\\madhya\\15\\229",
		"nextId": "cc/madhya/15/230",
		"prevId": "cc/madhya/15/228"
	},
	"verses": [
		{
			"roman": "annera saurabhya, varṇa--ati manorama\nrādhā-kṛṣṇa sākṣāt ihāṅ kariyāchena bhojana\n",
			"isProse": false
		}
	],
	"synonyms": "annera saurabhya—the flavor of the cooked rice; varṇa—color; ati manorama—very attractive; rādhā-kṛṣṇa—Lord Kṛṣṇa and Rādhārāṇī; sākṣāt—directly; ihāṅ—all this; kariyāchena bhojana—have eaten.",
	"translation": "\"The color of the rice is so attractive and its aroma so good that it appears Rādhā and Kṛṣṇa have directly taken it."
}