{
	"info": {
		"id": "cc\\antya\\4\\148",
		"nextId": "cc/antya/4/149",
		"prevId": "cc/antya/4/147"
	},
	"verses": [
		{
			"roman": "aparādha-bhaye teṅha milite nā āila\nmahāprabhu milibāre sei ṭhāñi gela\n",
			"isProse": false
		}
	],
	"synonyms": "aparādha-bhaye—out of fear of offenses; teṅha—Sanātana Gosvāmī; milite—to meet; nā āila—did not come forward; mahāprabhu—Śrī Caitanya Mahāprabhu; milibāre—to meet; sei ṭhāñi—to Sanātana Gosvāmī; gela—went.",
	"translation": "Out of fear of committing offenses, Sanātana Gosvāmī did not come forward to meet Śrī Caitanya Mahāprabhu. The Lord, however, went forward to meet him."
}