{
	"info": {
		"id": "cc\\antya\\4\\97",
		"nextId": "cc/antya/4/98",
		"prevId": "cc/antya/4/96"
	},
	"verses": [
		{
			"roman": "bhakti-siddhānta, śāstra-ācāra-nirṇaya\ntomā-dvāre karāibena, bujhiluṅ āśaya\n",
			"isProse": false
		}
	],
	"synonyms": "bhakti-siddhānta—conclusive decision in devotional service; śāstra—according to the scriptural injunctions; ācāra-nirṇaya—ascertainment of behavior; tomā-dvāre—by you; karāibena—will cause to be done; bujhiluṅ—I can understand; āśaya—His desire.",
	"translation": "\"I can understand from the words of Śrī Caitanya Mahāprabhu that He wants you to write books about the conclusive decision of devotional service and about the regulative principles ascertained from the revealed scriptures."
}