{
	"info": {
		"id": "cc\\madhya\\7\\49",
		"nextId": "cc/madhya/7/50",
		"prevId": "cc/madhya/7/48"
	},
	"verses": [
		{
			"roman": "svatantra-īśvara tumi karibe gamana\ndina katho raha, dekhi tomāra caraṇa'\n",
			"isProse": false
		}
	],
	"synonyms": "svatantra-īśvara—the independent Supreme Personality of Godhead; tumi—You; karibe—will make; gamana—departure; dina—days; katho—some; raha—please stay; dekhi—I may see; tomāra caraṇa—Your lotus feet.",
	"translation": "\"My dear Lord, You are the independent Supreme Personality of Godhead. Certainly You will depart. I know that. Still, I ask You to stay here a few days more so that I can see Your lotus feet.\""
}