{
	"info": {
		"id": "cc\\antya\\13\\66",
		"nextId": "cc/antya/13/67",
		"prevId": "cc/antya/13/65"
	},
	"verses": [
		{
			"roman": "jagadānanda-paṇḍita tabe ājñā māgilā\nsanātana prabhure kichu bheṭa-vastu dilā\n",
			"isProse": false
		}
	],
	"synonyms": "jagadānanda-paṇḍita—Jagadānanda Paṇḍita; tabe—at that time; ājñā māgilā—asked permission; sanātana—Sanātana Gosvāmī; prabhure—for Śrī Caitanya Mahāprabhu; kichu—some; bheṭa-vastu—gifts; dilā—presented.",
	"translation": "When Sanātana Gosvāmī granted permission for Jagadānanda to return to Jagannātha Purī, he gave Jagadānanda some gifts for Lord Caitanya Mahāprabhu."
}