{
	"info": {
		"id": "cc\\madhya\\12\\117",
		"nextId": "cc/madhya/12/118",
		"prevId": "cc/madhya/12/116"
	},
	"verses": [
		{
			"roman": "tumi bhāla kariyācha, śikhāha anyere\nei-mata bhāla karma seho yena kare\n",
			"isProse": false
		}
	],
	"synonyms": "tumi—you; bhāla kariyācha—have done well; śikhāha anyere—teach others; ei-mata—in this way; bhāla karma—good work; seho—he also; yena—so that; kare—performs.",
	"translation": "The Lord would say, \"You have done well. Please teach this to others so that they may act in the same way.\""
}