{
	"info": {
		"id": "cc\\antya\\2\\58",
		"nextId": "cc/antya/2/59",
		"prevId": "cc/antya/2/57"
	},
	"verses": [
		{
			"roman": "pāka-sāmagrī ānaha, āmi yāhā cāi'\nye māgila, śivānanda āni' dilā tāi\n",
			"isProse": false
		}
	],
	"synonyms": "pāka-sāmagrī ānaha—bring all cooking ingredients; āmi yāhā cāi—whatever I want; ye māgila—whatever he wanted; śivānanda—Śivānanda Sena; āni'-bringing; dilā tāi—delivered everything.",
	"translation": "Nṛsiṁhānanda Brahmacārī said to Śivānanda, \"Please bring whatever cooking ingredients I want.\" Thus Śivānanda Sena immediately brought whatever he asked for."
}