{
	"info": {
		"id": "cc\\madhya\\17\\220",
		"nextId": "cc/madhya/17/221",
		"prevId": "cc/madhya/17/219"
	},
	"verses": [
		{
			"roman": "āste-vyaste mahāprabhura lañā bahirvāsa\njala-seka kare aṅge, vastrera vātāsa\n",
			"isProse": false
		}
	],
	"synonyms": "āste-vyaste—with great haste; mahāprabhura—of Śrī Caitanya Mahāprabhu; lañā—taking; bahirvāsa—covering cloth; jala-seka kare—sprinkle water; aṅge—on the body; vastrera vātāsa—fanning with the cloth.",
	"translation": "They hastily sprinkled water over the Lord's body. Then they took up His cloth and began to fan Him with it."
}