{
	"info": {
		"id": "cc\\madhya\\17\\81",
		"nextId": "cc/madhya/17/82",
		"prevId": "cc/madhya/17/80"
	},
	"verses": [
		{
			"roman": "ei-mata balabhadra karena stavana\nprema-sevā kari' tuṣṭa kaila prabhura mana\n",
			"isProse": false
		}
	],
	"synonyms": "ei-mata—in this way; balabhadra—Balabhadra Bhaṭṭācārya; karena—offers; stavana—prayers; prema-sevā kari'-rendering service in love; tuṣṭa—pacified; kaila—made; prabhura—of Śrī Caitanya Mahāprabhu; mana—the mind.",
	"translation": "In this way Balabhadra Bhaṭṭācārya offered his prayers to the Lord. By rendering service unto Him in ecstatic love, He pacified the Lord's mind."
}