{
	"info": {
		"id": "cc\\adi\\8\\47",
		"nextId": "cc/adi/8/48",
		"prevId": "cc/adi/8/46"
	},
	"verses": [
		{
			"roman": "vistāra dekhiyā kichu saṅkoca haila mana\nsūtra-dhṛta kona līlā nā kaila varṇana\n",
			"isProse": false
		}
	],
	"synonyms": "vistāra—expansive; dekhiyā—seeing; kichu—some; saṅkoca—with hesitation; haila—became; mana—mind; sūtra-dhṛta—taking the aphorisms; kona—some; līlā—pastimes; nā—did not; kaila—make; varṇana—description.",
	"translation": "He saw them to be so extensive that he later felt that some had not been properly described."
}