{
	"info": {
		"id": "cc\\adi\\8\\56",
		"nextId": "cc/adi/8/57",
		"prevId": "cc/adi/8/55"
	},
	"verses": [
		{
			"roman": "sabāra sammāna-kartā, karena sabāra hita\nkauṭilya-mātsarya-hiṁsā nā jāne tāṅra cita\n",
			"isProse": false
		}
	],
	"synonyms": "sabāra—of all; sammāna-kartā—respectful; karena—does; sabāra—everyone's; hita—benefit; kauṭilya—diplomatic; mātsarya—jealousy; hiṁsā—envy; nā jāne—does not know; tāṅra—his; cita—heart.",
	"translation": "He was respectful to everyone and worked for the benefit of all. Diplomacy, envy and jealousy were unknown to his heart."
}